jupyterlab_nbconvert_nocode/__init__.py
jupyterlab_nbconvert_nocode/nbconvert_functions/__init__.py
jupyterlab_nbconvert_nocode/nbconvert_functions/hideinput/__init__.py
jupyterlab_nbconvert_nocode/nbconvert_functions/hideinput/exporters.py
jupyterlab_nbconvert_nocode/nbconvert_functions/hideinput/utils.py
jupyterlab_nbconvert_nocode/templates/hide_code_cells_html/conf.json
jupyterlab_nbconvert_nocode/templates/hide_code_cells_html/index.html.j2
jupyterlab_nbconvert_nocode/templates/hide_code_cells_html_email/conf.json
jupyterlab_nbconvert_nocode/templates/hide_code_cells_html_email/index.html.j2
jupyterlab_nbconvert_nocode/templates/hide_code_cells_pdf/conf.json
jupyterlab_nbconvert_nocode/templates/hide_code_cells_pdf/index.tex.j2
jupyterlab_nbconvert_nocode/tests/__init__.py
jupyterlab_nbconvert_nocode/tests/test_all.py
jupyterlab_nbconvert_nocode-0.4.1.data/data/share/jupyter/nbconvert/templates/hide_code_cells_html/conf.json
jupyterlab_nbconvert_nocode-0.4.1.data/data/share/jupyter/nbconvert/templates/hide_code_cells_html/index.html.j2
jupyterlab_nbconvert_nocode-0.4.1.data/data/share/jupyter/nbconvert/templates/hide_code_cells_html_email/conf.json
jupyterlab_nbconvert_nocode-0.4.1.data/data/share/jupyter/nbconvert/templates/hide_code_cells_html_email/index.html.j2
jupyterlab_nbconvert_nocode-0.4.1.data/data/share/jupyter/nbconvert/templates/hide_code_cells_pdf/conf.json
jupyterlab_nbconvert_nocode-0.4.1.data/data/share/jupyter/nbconvert/templates/hide_code_cells_pdf/index.tex.j2
jupyterlab_nbconvert_nocode-0.4.1.dist-info/METADATA
jupyterlab_nbconvert_nocode-0.4.1.dist-info/WHEEL
jupyterlab_nbconvert_nocode-0.4.1.dist-info/entry_points.txt
jupyterlab_nbconvert_nocode-0.4.1.dist-info/licenses/LICENSE
jupyterlab_nbconvert_nocode-0.4.1.dist-info/RECORD
