Metadata-Version: 2.1
Name: jupyterlab_nbconvert_nocode
Version: 0.4.1
Summary: A simple helper library with 2 NBConvert exporters for PDF/HTML export with no code cells
Project-URL: repository, https://github.com/timkpaine/jupyterlab_nbconvert_nocode
Project-URL: homepage, https://github.com/timkpaine/jupyterlab_nbconvert_nocode
Author-email: Tim Paine <t.paine154@gmail.com>
License:                                  Apache License
License-File: LICENSE
Keywords: Jupyter,JupyterLab,Notebook,Notebooks,Report,Reporting,Reports
Classifier: Development Status :: 4 - Beta
Classifier: Framework :: Jupyter
Classifier: Framework :: Jupyter :: JupyterLab
Classifier: License :: OSI Approved :: Apache Software License
Classifier: Programming Language :: Python
Classifier: Programming Language :: Python :: 3
Classifier: Programming Language :: Python :: 3.8
Classifier: Programming Language :: Python :: 3.9
Classifier: Programming Language :: Python :: 3.10
Classifier: Programming Language :: Python :: 3.11
Classifier: Programming Language :: Python :: 3.12
Requires-Python: >=3.8
Requires-Dist: jupyterlab>=3.5
Requires-Dist: nbconvert>=6.0.0
Provides-Extra: develop
Requires-Dist: black>=23; extra == 'develop'
Requires-Dist: check-manifest; extra == 'develop'
Requires-Dist: isort; extra == 'develop'
Requires-Dist: pytest; extra == 'develop'
Requires-Dist: pytest-cov; extra == 'develop'
Requires-Dist: ruff; extra == 'develop'
Provides-Extra: test
Requires-Dist: pytest; extra == 'test'
Requires-Dist: pytest-cov; extra == 'test'
